pyrandtoys/__init__.py
pyrandtoys/functions.py
pyrandtoys-1.0.0.dist-info/LICENSE.md
pyrandtoys-1.0.0.dist-info/METADATA
pyrandtoys-1.0.0.dist-info/WHEEL
pyrandtoys-1.0.0.dist-info/top_level.txt
pyrandtoys-1.0.0.dist-info/RECORD
